{
    "sumber": "PythonPemula.id",
    "penulis": "Hendra Gunawan",
    "tanggal": "2021-11-12",
    "judul": "Memahami dan Menggunakan Fungsi Print di Python",
    "tingkat_kesulitan": "Pemula",
    "tag": ["fungsi print", "pemula"],
    "konten": "Artikel ini menjelaskan tentang penggunaan fungsi print di Python. Fungsi print digunakan untuk menampilkan output ke layar.",
    "contoh": [
        {
            "tipe": "kode",
            "bahasa": "python",
            "isi": "print('Hello, world!')",
            "komentar": "Contoh dasar penggunaan fungsi print untuk mencetak teks sederhana"
        },
        {
            "tipe": "kode",
            "bahasa": "python",
            "isi": "name = 'Alice'\nprint('Hello,', name)",
            "komentar": "Contoh penggunaan fungsi print dengan variabel"
        },
        {
            "tipe": "kode",
            "bahasa": "python",
            "isi": "age = 25\nprint('I am', age, 'years old')",
            "komentar": "Contoh penggunaan fungsi print dengan variabel numerik"
        },
        {
            "tipe": "kode",
            "bahasa": "python",
            "isi": "print('Python', 'is', 'fun', sep='-')",
            "komentar": "Contoh penggunaan fungsi print dengan parameter sep untuk menentukan pemisah"
        },
        {
            "tipe": "kode",
            "bahasa": "python",
            "isi": "print('Hello', end='!')\nprint('World')",
            "komentar": "Contoh penggunaan fungsi print dengan parameter end untuk menentukan karakter akhir"
        }
    ],
    "topik": [
        {
            "topik": "Fungsi Print",
            "deskripsi": "Cara menggunakan fungsi print untuk mencetak teks dan variabel ke layar."
        },
        {
            "topik": "Parameter Sep",
            "deskripsi": "Cara menggunakan parameter sep untuk menentukan pemisah antara beberapa argumen dalam fungsi print."
        },
        {
            "topik": "Parameter End",
            "deskripsi": "Cara menggunakan parameter end untuk menentukan karakter yang ditambahkan di akhir output print."
        }
    ],
    "referensi": [
        {
            "judul": "Python Print Function - W3Schools",
            "url": "https://www.w3schools.com/python/ref_func_print.asp"
        },
        {
            "judul": "Understanding Python's Print Function - Real Python",
            "url": "https://realpython.com/python-print/"
        }
    ],
    "highlight": [
        "Penjelasan dasar tentang fungsi print",
        "Contoh-contoh praktis yang mudah dipahami"
    ],
    "error": [
        {
            "error": "TypeError",
            "deskripsi": "Kesalahan yang terjadi saat tipe data yang dicetak tidak sesuai dengan yang diharapkan.",
            "contoh": "print('Age: ' + 25)",
            "solusi": "Pastikan untuk mengonversi tipe data numerik ke string saat mencetak bersama teks, misalnya: print('Age: ' + str(25))."
        },
        {
            "error": "SyntaxError",
            "deskripsi": "Kesalahan yang terjadi saat sintaks print tidak sesuai dengan aturan Python.",
            "contoh": "print 'Hello, world!'",
            "solusi": "Pastikan untuk menggunakan tanda kurung saat memanggil fungsi print, misalnya: print('Hello, world!')."
        }
    ]
}
