[
    {
        "sumber": "pythonmudah.com",
        "penulis": "Fajar Prasetyo",
        "tanggal": "2023-05-18",
        "judul": "Menggunakan String di Python",
        "tingkat_kesulitan": "Pemula",
        "tag": ["python", "string", "dasar"],
        "konten": "Artikel ini menjelaskan cara menggunakan string di Python, termasuk cara membuat, mengakses, memanipulasi, dan memformat string.",
        "pertanyaan": [
            {
                "question": "Bagaimana cara membuat string di Python?",
                "answer": "Anda bisa membuat string dengan menggunakan tanda kutip tunggal atau ganda. Contohnya: `str1 = 'Hello'` atau `str2 = \"World\"`."
            },
            {
                "question": "Bagaimana cara mengakses karakter dalam string?",
                "answer": "Anda bisa mengakses karakter dalam string dengan menggunakan indeks. Contohnya: `str1[0]` untuk karakter pertama."
            },
            {
                "question": "Bagaimana cara menggabungkan dua string?",
                "answer": "Anda bisa menggabungkan dua string dengan menggunakan operator `+`. Contohnya: `str1 + str2`."
            },
            {
                "question": "Bagaimana cara mengulang string beberapa kali?",
                "question_code": "str1 * 3",
                "answer": "Anda bisa mengulang string beberapa kali dengan menggunakan operator `*`. Contohnya: `str1 * 3`.",
                "answer_code": "str1 * 3"
            },
            {
                "question": "Bagaimana cara memeriksa apakah substring ada dalam string?",
                "question_code": "'Hello' in str1",
                "answer": "Anda bisa memeriksa apakah substring ada dalam string dengan menggunakan operator `in`. Contohnya: `'Hello' in str1`.",
                "answer_code": "'Hello' in str1"
            },
            {
                "question": "Bagaimana cara mengganti substring dalam string?",
                "question_code": "str1.replace('Hello', 'Hi')",
                "answer": "Anda bisa mengganti substring dalam string dengan menggunakan metode `replace()`. Contohnya: `str1.replace('Hello', 'Hi')`.",
                "answer_code": "str1.replace('Hello', 'Hi')"
            },
            {
                "question": "Bagaimana cara mengubah string menjadi huruf besar?",
                "question_code": "str1.upper()",
                "answer": "Anda bisa mengubah string menjadi huruf besar dengan menggunakan metode `upper()`. Contohnya: `str1.upper()`.",
                "answer_code": "str1.upper()"
            },
            {
                "question": "Bagaimana cara menghapus spasi di awal dan akhir string?",
                "question_code": "str1.strip()",
                "answer": "Anda bisa menghapus spasi di awal dan akhir string dengan menggunakan metode `strip()`. Contohnya: `str1.strip()`.",
                "answer_code": "str1.strip()"
            },
            {
                "question": "Bagaimana cara memformat string dengan variabel?",
                "question_code": "\"Hello, {}\".format(name)",
                "answer": "Anda bisa memformat string dengan variabel menggunakan metode `format()`. Contohnya: `\"Hello, {}\".format(name)`.",
                "answer_code": "\"Hello, {}\".format(name)"
            }
        ]
    },
    {
        "sumber": "belajarpemrogramanpython.com",
        "penulis": "Mira Handayani",
        "tanggal": "2024-04-22",
        "judul": "Penggunaan List Comprehensions di Python",
        "tingkat_kesulitan": "Pemula",
        "tag": ["python", "list comprehensions", "dasar"],
        "konten": "Artikel ini menjelaskan cara menggunakan list comprehensions di Python untuk membuat dan memanipulasi list dengan sintaks yang lebih ringkas.",
        "pertanyaan": [
            {
                "question": "Apa itu list comprehensions di Python?",
                "answer": "List comprehensions adalah cara singkat untuk membuat list baru dari iterable yang ada menggunakan satu baris kode."
            },
            {
                "question": "Bagaimana cara membuat list comprehension sederhana?",
                "answer": "Anda bisa membuat list comprehension sederhana dengan sintaks `[expression for item in iterable]`. Contohnya: `[x for x in range(5)]`."
            },
            {
                "question": "Bagaimana cara menambahkan kondisi ke dalam list comprehension?",
                "question_code": "[x for x in range(10) if x % 2 == 0]",
                "answer": "Anda bisa menambahkan kondisi ke dalam list comprehension dengan sintaks `[expression for item in iterable if condition]`. Contohnya: `[x for x in range(10) if x % 2 == 0]`.",
                "answer_code": "[x for x in range(10) if x % 2 == 0]"
            },
            {
                "question": "Bagaimana cara membuat list comprehension dengan fungsi?",
                "question_code": "[x**2 for x in range(10)]",
                "answer": "Anda bisa membuat list comprehension dengan menggunakan fungsi di dalam ekspresi. Contohnya: `[x**2 for x in range(10)]`.",
                "answer_code": "[x**2 for x in range(10)]"
            },
            {
                "question": "Bagaimana cara membuat list comprehension dari list yang ada?",
                "question_code": "numbers = [1, 2, 3, 4, 5]\nsquares = [x**2 for x in numbers]",
                "answer": "Anda bisa membuat list comprehension dari list yang ada dengan menggunakan list sebagai iterable. Contohnya: `[x**2 for x in numbers]`.",
                "answer_code": "squares = [x**2 for x in numbers]"
            },
            {
                "question": "Bagaimana cara membuat nested list comprehensions?",
                "question_code": "[[x, y] for x in range(3) for y in range(3)]",
                "answer": "Anda bisa membuat nested list comprehensions dengan menggunakan dua loop for di dalam satu list comprehension. Contohnya: `[[x, y] for x in range(3) for y in range(3)]`.",
                "answer_code": "[[x, y] for x in range(3) for y in range(3)]"
            },
            {
                "question": "Bagaimana cara menggunakan list comprehension untuk memanipulasi string?",
                "question_code": "[char.upper() for char in 'hello']",
                "answer": "Anda bisa menggunakan list comprehension untuk memanipulasi string dengan iterasi karakter di dalam string. Contohnya: `[char.upper() for char in 'hello']`.",
                "answer_code": "[char.upper() for char in 'hello']"
            },
            {
                "question": "Bagaimana cara membuat list comprehension dari dictionary?",
                "question_code": "{k: v**2 for k, v in {'a': 1, 'b': 2}.items()}",
                "answer": "Anda bisa membuat list comprehension dari dictionary dengan menggunakan `.items()` untuk iterasi kunci dan nilai. Contohnya: `{k: v**2 for k, v in {'a': 1, 'b': 2}.items()}`.",
                "answer_code": "{k: v**2 for k, v in {'a': 1, 'b': 2}.items()}"
            },
            {
                "question": "Bagaimana cara membuat set comprehension di Python?",
                "question_code": "{x for x in range(5)}",
                "answer": "Anda bisa membuat set comprehension dengan menggunakan tanda kurung kurawal `{}`. Contohnya: `{x for x in range(5)}`.",
                "answer_code": "{x for x in range(5)}"
            }
        ]
    }
]
