[
    {
        "sumber": "Python List Operations",
        "penulis": "Ava Johnson",
        "tanggal": "2024-11-10",
        "judul": "Cara Efektif Menambahkan Elemen ke List Menggunakan `append()`",
        "tingkat_kesulitan": "Intermediate",
        "tag": ["Python", "Lists", "append"],
        "konten": "Panduan ini menjelaskan cara menambahkan elemen ke dalam list di Python dengan menggunakan method `append()`. Ini adalah metode yang sangat berguna untuk menambah elemen baru di akhir list.",
        "pertanyaan": [
            {
                "question": "Bagaimana cara menambahkan elemen `True` ke dalam list menggunakan method `append()`?",
                "answer": "Gunakan method `append()` seperti berikut: `my_list.append(True)` untuk menambahkan elemen `True` ke akhir list `my_list`."
            },
            {
                "question": "Apa yang terjadi jika Anda menggunakan `append()` pada sebuah objek yang bukan list?",
                "answer": "Jika Anda menggunakan `append()` pada tipe data selain list, seperti integer atau string, Anda akan mendapatkan error. Method `append()` hanya berlaku untuk objek list di Python."
            },
            {
                "question": "Bagaimana menambahkan tuple `(5, 6)` sebagai elemen di dalam list menggunakan `append()`?",
                "answer": "Untuk menambahkan tuple `(5, 6)` sebagai elemen di akhir list, gunakan `append()` seperti ini: `my_list.append((5, 6))`. Ini akan menambahkan tuple sebagai satu elemen di akhir `my_list`."
            },
            {
                "question": "Kenapa saya mendapatkan error 'AttributeError: 'str' object has no attribute 'append''?",
                "question_code": "text = 'Python'\ntext.append(' Rocks')",
                "answer": "Error ini terjadi karena `append()` tidak dapat digunakan pada string. String di Python bersifat immutable dan tidak mendukung method `append()`. Anda harus menggunakan concatenation dengan `+` untuk menambahkan teks.",
                "answer_code": "text = 'Python'\ntext += ' Rocks'"
            },
            {
                "question": "Kenapa terjadi error 'TypeError: append() missing 1 required positional argument'?",
                "question_code": "my_list = [10, 20]\nmy_list.append()",
                "answer": "Error ini terjadi karena `append()` membutuhkan satu argumen yang akan ditambahkan ke dalam list. Anda harus memberikan argumen saat memanggil `append()`.",
                "answer_code": "my_list = [10, 20]\nmy_list.append(30)"
            },
            {
                "question": "Kenapa saya mendapatkan error 'TypeError: 'dict' object does not support item assignment'?",
                "question_code": "my_dict = {'key': 'value'}\nmy_dict.append('new_item')",
                "answer": "Error ini terjadi karena `append()` tidak dapat digunakan pada dictionary. Method ini hanya berlaku untuk list. Untuk menambahkan item ke dictionary, gunakan metode `update()` atau penugasan langsung.",
                "answer_code": "my_dict = {'key': 'value'}\nmy_dict['new_key'] = 'new_value'"
            },
            {
                "question": "Kenapa saya mendapatkan error 'TypeError: append() takes exactly one argument (2 given)'?",
                "question_code": "my_list = [1, 2, 3]\nmy_list.append(4, 5)",
                "answer": "Error ini terjadi karena `append()` hanya menerima satu argumen. Untuk menambahkan beberapa elemen, gunakan `extend()` atau tambahkan elemen satu per satu dengan `append()`.",
                "answer_code": "my_list = [1, 2, 3]\nmy_list.append(4)\nmy_list.append(5)"
            },
            {
                "question": "Kenapa saya mendapatkan error 'IndexError: list index out of range'?",
                "question_code": "my_list = [1, 2, 3]\nmy_list[4] = 5",
                "answer": "Error ini terjadi karena Anda mencoba mengakses atau mengubah elemen di indeks yang tidak ada. Untuk menambahkan elemen, gunakan `append()` bukan assignment.",
                "answer_code": "my_list = [1, 2, 3]\nmy_list.append(5)"
            }
        ]
    },
    {
        "sumber": "Advanced Python Techniques",
        "penulis": "Oliver Smith",
        "tanggal": "2024-10-20",
        "judul": "Menambahkan Elemen ke List dengan `append()` dan Penanganan Error",
        "tingkat_kesulitan": "Intermediate",
        "tag": ["Python", "Lists", "append"],
        "konten": "Artikel ini membahas cara menggunakan method `append()` untuk menambahkan elemen ke dalam list serta menangani beberapa error umum yang mungkin terjadi saat menggunakan method ini.",
        "pertanyaan": [
            {
                "question": "Bagaimana cara menambahkan elemen `42` ke dalam list yang sudah ada dengan `append()`?",
                "answer": "Gunakan method `append()` seperti berikut: `my_list.append(42)` untuk menambahkan elemen `42` ke akhir list `my_list`."
            },
            {
                "question": "Apa yang akan terjadi jika Anda mencoba menambahkan objek ke dalam tuple menggunakan `append()`?",
                "answer": "Jika Anda mencoba menggunakan `append()` pada tuple, Anda akan mendapatkan error karena tuple adalah tipe data yang tidak dapat dimodifikasi setelah dibuat. `append()` hanya berlaku untuk list."
            },
            {
                "question": "Bagaimana menambahkan dictionary `{'key': 'value'}` ke dalam list menggunakan `append()`?",
                "answer": "Untuk menambahkan dictionary ke dalam list, gunakan `append()` seperti ini: `my_list.append({'key': 'value'})`. Ini akan menambahkan dictionary sebagai satu elemen di akhir `my_list`."
            },
            {
                "question": "Kenapa saya mendapatkan error 'AttributeError: 'int' object has no attribute 'append''?",
                "question_code": "num = 100\nnum.append(200)",
                "answer": "Error ini terjadi karena `append()` tidak dapat digunakan pada integer. Method ini hanya berlaku untuk list. Pastikan Anda menggunakan `append()` pada list.",
                "answer_code": "my_list = [100]\nmy_list.append(200)"
            },
            {
                "question": "Kenapa terjadi error 'TypeError: append() missing 1 required positional argument'?",
                "question_code": "my_list = [1, 2]\nmy_list.append()",
                "answer": "Error ini terjadi karena `append()` membutuhkan satu argumen yang akan ditambahkan ke dalam list. Anda harus memberikan argumen yang sesuai saat memanggil `append()`.",
                "answer_code": "my_list = [1, 2]\nmy_list.append(3)"
            },
            {
                "question": "Kenapa terjadi error 'TypeError: 'list' object does not support item assignment'?",
                "question_code": "my_list = [1, 2, 3]\nmy_list.append([4, 5])",
                "answer": "Error ini terjadi karena `append()` tidak dapat menambahkan beberapa elemen sekaligus. Jika Anda ingin menambahkan beberapa elemen, gunakan `extend()`.",
                "answer_code": "my_list = [1, 2, 3]\nmy_list.extend([4, 5])"
            },
            {
                "question": "Kenapa saya mendapatkan error 'IndexError: list index out of range' saat mencoba menambahkan elemen?",
                "question_code": "my_list = [1, 2]\nmy_list[5] = 6",
                "answer": "Error ini terjadi karena Anda mencoba mengakses atau mengubah elemen di indeks yang tidak ada. Untuk menambahkan elemen, gunakan `append()` atau `extend()`.",
                "answer_code": "my_list = [1, 2]\nmy_list.append(6)"
            }
        ]
    }
]
