[
    {
        "sumber": "Python Documentation",
        "penulis": "Guido van Rossum",
        "tanggal": "2024-07-27",
        "judul": "Menggunakan min() dan max() untuk Mendapatkan Nilai Minimum dan Maksimum dalam List di Python",
        "tingkat_kesulitan": "Basic",
        "tag": ["Python", "Lists", "Min", "Max"],
        "konten": "Artikel ini menjelaskan cara menggunakan fungsi min() dan max() untuk mendapatkan nilai minimum dan maksimum dari list di Python. Termasuk contoh kode dan tips praktis.",
        "pertanyaan": [
            {
                "question": "Apa fungsi dari min() dalam list di Python?",
                "answer": "Fungsi min() digunakan untuk mendapatkan nilai minimum dalam list. Ini mengembalikan elemen dengan nilai terkecil dalam list."
            },
            {
                "question": "Bagaimana cara mendapatkan nilai maksimum dari list menggunakan max()?",
                "answer": "Gunakan fungsi max() dengan memberikan list sebagai argumen. Fungsi ini mengembalikan nilai maksimum dari list."
            },
            {
                "question": "Apa yang terjadi jika min() atau max() dipanggil pada list kosong?",
                "answer": "Memanggil min() atau max() pada list kosong akan menghasilkan ValueError, karena tidak ada elemen untuk dibandingkan."
            },
            {
                "question": "Mengapa kode berikut ini menghasilkan error?",
                "question_code": "data = [3, 5, 1, 2]\nsmallest = min data",
                "answer": "Kode tersebut menghasilkan error karena fungsi min() harus dipanggil dengan tanda kurung.",
                "answer_code": "data = [3, 5, 1, 2]\nsmallest = min(data)"
            },
            {
                "question": "Mengapa kode berikut ini tidak berfungsi untuk mendapatkan nilai maksimum dalam list?",
                "question_code": "values = [10, 20, 30]\nmax_value = max(values]",
                "answer": "Kode tersebut tidak berfungsi karena tanda kurung penutup fungsi max() adalah kurung siku, bukan kurung biasa.",
                "answer_code": "values = [10, 20, 30]\nmax_value = max(values)"
            },
            {
                "question": "Apa yang salah dengan kode ini untuk mendapatkan nilai minimum dari list?",
                "question_code": "numbers = [11, 22, 33]\nmin_number = min((numbers)",
                "answer": "Kode tersebut salah karena ada tanda kurung ganda yang tidak perlu pada fungsi min().",
                "answer_code": "numbers = [11, 22, 33]\nmin_number = min(numbers)"
            },
            {
                "question": "Mengapa kode berikut ini menghasilkan error?",
                "question_code": "heights = [150, 175, 160]\nmin_height = min(heights] ",
                "answer": "Kode tersebut menghasilkan error karena tanda kurung penutup pada fungsi min() adalah kurung siku, bukan kurung biasa.",
                "answer_code": "heights = [150, 175, 160]\nmin_height = min(heights)"
            },
            {
                "question": "Mengapa kode berikut ini tidak menghasilkan nilai maksimum yang benar?",
                "question_code": "temps = [32, 21, 45, 50]\nmax_temp = max temps",
                "answer": "Kode tersebut tidak menghasilkan nilai maksimum yang benar karena fungsi max() harus dipanggil dengan tanda kurung.",
                "answer_code": "temps = [32, 21, 45, 50]\nmax_temp = max(temps)"
            },
            {
                "question": "Apa yang salah dengan kode berikut ini saat mencari nilai minimum?",
                "question_code": "ages = [25, 30, 35, 40]\nmin_age = min(ages))",
                "answer": "Kode tersebut salah karena ada tanda kurung ganda di akhir panggilan fungsi min().",
                "answer_code": "ages = [25, 30, 35, 40]\nmin_age = min(ages)"
            }
        ]
    },
    {
        "sumber": "Real Python",
        "penulis": "Alex Smith",
        "tanggal": "2024-07-27",
        "judul": "Fungsi min() dan max() di Python: Menemukan Nilai Ekstrem dalam List",
        "tingkat_kesulitan": "Basic",
        "tag": ["Python", "Lists", "Min", "Max"],
        "konten": "Panduan ini membahas cara menggunakan fungsi min() dan max() untuk menemukan nilai minimum dan maksimum dalam list, serta memberikan beberapa contoh aplikasi praktis.",
        "pertanyaan": [
            {
                "question": "Bagaimana min() dan max() berfungsi untuk menemukan nilai ekstrem dalam list?",
                "answer": "Fungsi min() mengembalikan nilai terkecil dalam list, sedangkan fungsi max() mengembalikan nilai terbesar. Keduanya membandingkan elemen dalam list untuk menentukan nilai ekstrem."
            },
            {
                "question": "Dapatkah min() dan max() digunakan pada list dengan elemen yang memiliki tipe data berbeda?",
                "answer": "Min() dan max() dapat digunakan pada list dengan elemen yang memiliki tipe data berbeda jika tipe data tersebut dapat dibandingkan satu sama lain. Jika tidak, akan menghasilkan TypeError."
            },
            {
                "question": "Apa yang harus diperhatikan ketika menggunakan min() dan max() pada list yang berisi objek kustom?",
                "answer": "Jika menggunakan min() dan max() pada list yang berisi objek kustom, pastikan objek tersebut memiliki metode perbandingan (__lt__, __le__, __gt__, __ge__) untuk menghindari TypeError."
            },
            {
                "question": "Mengapa kode berikut ini menghasilkan error?",
                "question_code": "weights = [55, 65, 75, 85]\nlightest = min(weights,)",
                "answer": "Kode tersebut menghasilkan error karena ada tanda koma yang tidak perlu setelah argumen pada fungsi min()."
            },
            {
                "question": "Apa yang salah dengan kode ini saat mencoba menghitung nilai maksimum dalam list?",
                "question_code": "prices = [99, 89, 79]\nmax_price = max(prices).",
                "answer": "Kode tersebut salah karena ada tanda titik yang tidak perlu setelah fungsi max()."
            },
            {
                "question": "Mengapa kode berikut tidak dapat menghitung nilai minimum dalam list?",
                "question_code": "grades = [88, 92, 79]\nmin_grade = minimum(grades)",
                "answer": "Kode tersebut tidak dapat menghitung nilai minimum dalam list karena nama fungsi yang benar adalah min(), bukan minimum()."
            },
            {
                "question": "Mengapa kode berikut ini tidak berfungsi?",
                "question_code": "distances = [5.5, 3.2, 7.8]\nmin_distance = min(distances))",
                "answer": "Kode tersebut tidak berfungsi karena ada tanda kurung ganda di akhir panggilan fungsi min().",
                "answer_code": "distances = [5.5, 3.2, 7.8]\nmin_distance = min(distances)"
            },
            {
                "question": "Mengapa kode berikut tidak menghasilkan nilai maksimum yang benar?",
                "question_code": "sales = [1200, 2300, 3100, 1800]\nmax_sale = max(sales ",
                "answer": "Kode tersebut tidak menghasilkan nilai maksimum yang benar karena tanda kurung penutup fungsi max() hilang.",
                "answer_code": "sales = [1200, 2300, 3100, 1800]\nmax_sale = max(sales)"
            },
            {
                "question": "Apa yang salah dengan kode berikut ini saat mencari nilai minimum?",
                "question_code": "profits = [15000, 20000, 30000]\nmin_profit = min(profits))",
                "answer": "Kode tersebut salah karena ada tanda kurung ganda di akhir panggilan fungsi min().",
                "answer_code": "profits = [15000, 20000, 30000]\nmin_profit = min(profits)"
            }
        ]
    }
]
